snek/__init__.py
snek/pytest_helpers/__init__.py
snek/snektest/__init__.py
snek/snektest/cli.py
snek/snektest/possible_api_1.py
snek/snektest/presentation.py
snek/snektest/results.py
snek/snektest/runner.py
sneklib-0.0.1.dist-info/METADATA
sneklib-0.0.1.dist-info/WHEEL
sneklib-0.0.1.dist-info/licenses/LICENSE
sneklib-0.0.1.dist-info/RECORD
