Metadata-Version: 2.3
Name: sneklib
Version: 0.0.1
Summary: Library with various libs, with type-safety and async support
License-File: LICENSE
Classifier: License :: OSI Approved :: MIT License
Classifier: Operating System :: OS Independent
Classifier: Programming Language :: Python :: 3
Requires-Python: >=3.12
Provides-Extra: snektest
Requires-Dist: colorama; extra == 'snektest'
